["[\n  {\n    \"company\": \"adidas\",\n    \"Shop\": \"adidas\",\n    \"LABLE\": \"60%\",\n    \"Desc\": \"Shop at adidas: Up to 60% off in the End of Year Sale\",\n    \"Code\": \"Discount Displayed on Site\",\n    \"Souce\": \"https://www.adidas.com/us\",\n    \"LOGO\": \"/dbt/uploads/logos/adidas.jpg?ts=1669899628\",\n    \"Effective_date\": \"2023-01-02T00:57:00-08:00\",\n    \"check_date\": \"NA\",\n    \"Expire_date\": \"2023-01-08T23:59:59-08:00\",\n    \"img_link\": \"https://coupons.cnet.com/image/eyJrZXkiOiJjbnQvdXBsb2Fkcy9sb2dvcy9hZGlkYXMuanBnIiwib3V0cHV0Rm9ybWF0IjoiIiwiZWRpdHMiOnsicmVzaXplIjp7IndpZHRoIjoxMTcwfX19?ts=1669899628\",\n    \"cmp_desc\": \"NA\",\n    \"cmp_title\": \"adidas Promo Code – Save 60% in January 2023\"\n  },\n  {\n    \"company\": \"adidas\",\n    \"Shop\": \"adidas\",\n    \"LABLE\": \"30%\",\n    \"Desc\": \"Save Big: 30% off Your Purchase\",\n    \"Code\": \"GIFT\",\n    \"Souce\": \"https://www.adidas.com/us\",\n    \"LOGO\": \"/dbt/uploads/logos/adidas.jpg?ts=1669899628\",\n    \"Effective_date\": \"2022-12-22T10:29:00-08:00\",\n    \"check_date\": \"NA\",\n    \"Expire_date\": \"2023-01-11T12:59:00-08:00\",\n    \"img_link\": \"https://coupons.cnet.com/image/eyJrZXkiOiJjbnQvdXBsb2Fkcy9sb2dvcy9hZGlkYXMuanBnIiwib3V0cHV0Rm9ybWF0IjoiIiwiZWRpdHMiOnsicmVzaXplIjp7IndpZHRoIjoxMTcwfX19?ts=1669899628\",\n    \"cmp_desc\": \"NA\",\n    \"cmp_title\": \"adidas Promo Code – Save 60% in January 2023\"\n  },\n  {\n    \"company\": \"adidas\",\n    \"Shop\": \"adidas\",\n    \"LABLE\": \"15%\",\n    \"Desc\": \"15% off at adidas\",\n    \"Code\": \"Sign Up for Email Newsletter to Receive Discount\",\n    \"Souce\": \"https://www.adidas.com/us\",\n    \"LOGO\": \"/dbt/uploads/logos/adidas.jpg?ts=1669899628\",\n    \"Effective_date\": \"2022-10-29T04:11:00-07:00\",\n    \"check_date\": \"2022-12-27T00:19:11-08:00\",\n    \"Expire_date\": \"2023-12-31T23:59:00-08:00\",\n    \"img_link\": \"https://coupons.cnet.com/image/eyJrZXkiOiJjbnQvdXBsb2Fkcy9sb2dvcy9hZGlkYXMuanBnIiwib3V0cHV0Rm9ybWF0IjoiIiwiZWRpdHMiOnsicmVzaXplIjp7IndpZHRoIjoxMTcwfX19?ts=1669899628\",\n    \"cmp_desc\": \"NA\",\n    \"cmp_title\": \"adidas Promo Code – Save 60% in January 2023\"\n  },\n  {\n    \"company\": \"adidas\",\n    \"Shop\": \"adidas\",\n    \"LABLE\": \"15%\",\n    \"Desc\": \"Grab 15% off Your Order\",\n    \"Code\": \"Sign Up for adidas AdiClub to Receive Discount\",\n    \"Souce\": \"https://www.adidas.com/us\",\n    \"LOGO\": \"/dbt/uploads/logos/adidas.jpg?ts=1669899628\",\n    \"Effective_date\": \"2021-08-15T22:59:00-07:00\",\n    \"check_date\": \"2022-12-04T00:04:57-08:00\",\n    \"Expire_date\": \"2023-12-31T23:59:00-08:00\",\n    \"img_link\": \"https://coupons.cnet.com/image/eyJrZXkiOiJjbnQvdXBsb2Fkcy9sb2dvcy9hZGlkYXMuanBnIiwib3V0cHV0Rm9ybWF0IjoiIiwiZWRpdHMiOnsicmVzaXplIjp7IndpZHRoIjoxMTcwfX19?ts=1669899628\",\n    \"cmp_desc\": \"NA\",\n    \"cmp_title\": \"adidas Promo Code – Save 60% in January 2023\"\n  },\n  {\n    \"company\": \"adidas\",\n    \"Shop\": \"adidas\",\n    \"LABLE\": \"30%\",\n    \"Desc\": \"Grab 30% off Medical Professionals, First Responders, Nurses, Military Members & Teachers\",\n    \"Code\": \"Verify your status with ID.me to Receive Discount\",\n    \"Souce\": \"https://www.adidas.com/us\",\n    \"LOGO\": \"/dbt/uploads/logos/adidas.jpg?ts=1669899628\",\n    \"Effective_date\": \"2021-03-05T00:24:00-08:00\",\n    \"check_date\": \"2022-12-14T00:05:52-08:00\",\n    \"Expire_date\": \"2023-12-31T23:59:00-08:00\",\n    \"img_link\": \"https://coupons.cnet.com/image/eyJrZXkiOiJjbnQvdXBsb2Fkcy9sb2dvcy9hZGlkYXMuanBnIiwib3V0cHV0Rm9ybWF0IjoiIiwiZWRpdHMiOnsicmVzaXplIjp7IndpZHRoIjoxMTcwfX19?ts=1669899628\",\n    \"cmp_desc\": \"NA\",\n    \"cmp_title\": \"adidas Promo Code – Save 60% in January 2023\"\n  },\n  {\n    \"company\": \"adidas\",\n    \"Shop\": \"adidas\",\n    \"LABLE\": \"$20\",\n    \"Desc\": \"$20 off Select Items at adidas\",\n    \"Code\": \"MASKUP\",\n    \"Souce\": \"https://www.adidas.com/us\",\n    \"LOGO\": \"/dbt/uploads/logos/adidas.jpg?ts=1669899628\",\n    \"Effective_date\": \"2021-04-13T12:22:00-07:00\",\n    \"check_date\": \"2022-12-12T00:11:11-08:00\",\n    \"Expire_date\": \"2023-01-23T21:33:00-08:00\",\n    \"img_link\": \"https://coupons.cnet.com/image/eyJrZXkiOiJjbnQvdXBsb2Fkcy9sb2dvcy9hZGlkYXMuanBnIiwib3V0cHV0Rm9ybWF0IjoiIiwiZWRpdHMiOnsicmVzaXplIjp7IndpZHRoIjoxMTcwfX19?ts=1669899628\",\n    \"cmp_desc\": \"NA\",\n    \"cmp_title\": \"adidas Promo Code – Save 60% in January 2023\"\n  },\n  {\n    \"company\": \"adidas\",\n    \"Shop\": \"adidas\",\n    \"LABLE\": \"NA\",\n    \"Desc\": \"Seasonal Savings: Head-to-toe outfits for the family. Get inspired with our top clothing picks this holiday season. Find jackets, tracksuits and more\",\n    \"Code\": \"Discount Displayed on Site\",\n    \"Souce\": \"https://www.adidas.com/us\",\n    \"LOGO\": \"/dbt/uploads/logos/adidas.jpg?ts=1669899628\",\n    \"Effective_date\": \"2021-10-27T00:00:00-07:00\",\n    \"check_date\": \"NA\",\n    \"Expire_date\": \"2023-12-31T23:59:00-08:00\",\n    \"img_link\": \"https://coupons.cnet.com/image/eyJrZXkiOiJjbnQvdXBsb2Fkcy9sb2dvcy9hZGlkYXMuanBnIiwib3V0cHV0Rm9ybWF0IjoiIiwiZWRpdHMiOnsicmVzaXplIjp7IndpZHRoIjoxMTcwfX19?ts=1669899628\",\n    \"cmp_desc\": \"NA\",\n    \"cmp_title\": \"adidas Promo Code – Save 60% in January 2023\"\n  },\n  {\n    \"company\": \"adidas\",\n    \"Shop\": \"adidas\",\n    \"LABLE\": \"$30\",\n    \"Desc\": \"adidas Coupon: Get 2 for $30 on Face Masks\",\n    \"Code\": \"MASKUP\",\n    \"Souce\": \"https://www.adidas.com/us\",\n    \"LOGO\": \"/dbt/uploads/logos/adidas.jpg?ts=1669899628\",\n    \"Effective_date\": \"2021-05-19T02:37:00-07:00\",\n    \"check_date\": \"2022-11-25T09:18:27-08:00\",\n    \"Expire_date\": \"2023-12-31T23:59:00-08:00\",\n    \"img_link\": \"https://coupons.cnet.com/image/eyJrZXkiOiJjbnQvdXBsb2Fkcy9sb2dvcy9hZGlkYXMuanBnIiwib3V0cHV0Rm9ybWF0IjoiIiwiZWRpdHMiOnsicmVzaXplIjp7IndpZHRoIjoxMTcwfX19?ts=1669899628\",\n    \"cmp_desc\": \"NA\",\n    \"cmp_title\": \"adidas Promo Code – Save 60% in January 2023\"\n  },\n  {\n    \"company\": \"adidas\",\n    \"Shop\": \"adidas\",\n    \"LABLE\": \"NA\",\n    \"Desc\": \"Don't miss this Deal at adidas for Free Shipping plus 30 Day Returns for adiClub Members\",\n    \"Code\": \"Discount Applied at Checkout\",\n    \"Souce\": \"https://www.adidas.com/us\",\n    \"LOGO\": \"/dbt/uploads/logos/adidas.jpg?ts=1669899628\",\n    \"Effective_date\": \"2021-01-05T05:21:00-08:00\",\n    \"check_date\": \"2022-10-20T14:04:59-07:00\",\n    \"Expire_date\": \"2023-12-31T23:59:00-08:00\",\n    \"img_link\": \"https://coupons.cnet.com/image/eyJrZXkiOiJjbnQvdXBsb2Fkcy9sb2dvcy9hZGlkYXMuanBnIiwib3V0cHV0Rm9ybWF0IjoiIiwiZWRpdHMiOnsicmVzaXplIjp7IndpZHRoIjoxMTcwfX19?ts=1669899628\",\n    \"cmp_desc\": \"NA\",\n    \"cmp_title\": \"adidas Promo Code – Save 60% in January 2023\"\n  },\n  {\n    \"company\": \"adidas\",\n    \"Shop\": \"adidas\",\n    \"LABLE\": \"NA\",\n    \"Desc\": \"Save at adidas - Shop Exclusive Gear for Club Members\",\n    \"Code\": \"Discount Displayed on Site\",\n    \"Souce\": \"https://www.adidas.com/us\",\n    \"LOGO\": \"/dbt/uploads/logos/adidas.jpg?ts=1669899628\",\n    \"Effective_date\": \"2021-06-07T18:29:00-07:00\",\n    \"check_date\": \"2022-10-11T17:34:20-07:00\",\n    \"Expire_date\": \"NA\",\n    \"img_link\": \"https://coupons.cnet.com/image/eyJrZXkiOiJjbnQvdXBsb2Fkcy9sb2dvcy9hZGlkYXMuanBnIiwib3V0cHV0Rm9ybWF0IjoiIiwiZWRpdHMiOnsicmVzaXplIjp7IndpZHRoIjoxMTcwfX19?ts=1669899628\",\n    \"cmp_desc\": \"NA\",\n    \"cmp_title\": \"adidas Promo Code – Save 60% in January 2023\"\n  },\n  {\n    \"company\": \"adidas\",\n    \"Shop\": \"adidas\",\n    \"LABLE\": \"60%\",\n    \"Desc\": \"Seasonal Savings: Up to 60% Off on Ultraboost Shoes\",\n    \"Code\": \"Discount Displayed on Site\",\n    \"Souce\": \"https://www.adidas.com/us\",\n    \"LOGO\": \"/dbt/uploads/logos/adidas.jpg?ts=1669899628\",\n    \"Effective_date\": \"2022-11-30T02:58:00-08:00\",\n    \"check_date\": \"2022-12-11T15:59:47-08:00\",\n    \"Expire_date\": \"2023-01-23T05:00:00-08:00\",\n    \"img_link\": \"https://coupons.cnet.com/image/eyJrZXkiOiJjbnQvdXBsb2Fkcy9sb2dvcy9hZGlkYXMuanBnIiwib3V0cHV0Rm9ybWF0IjoiIiwiZWRpdHMiOnsicmVzaXplIjp7IndpZHRoIjoxMTcwfX19?ts=1669899628\",\n    \"cmp_desc\": \"NA\",\n    \"cmp_title\": \"adidas Promo Code – Save 60% in January 2023\"\n  },\n  {\n    \"company\": \"adidas\",\n    \"Shop\": \"adidas\",\n    \"LABLE\": \"60%\",\n    \"Desc\": \"Don't miss this Deal at adidas for Up to 60% Off on Fleece\",\n    \"Code\": \"Discount Displayed on Site\",\n    \"Souce\": \"https://www.adidas.com/us\",\n    \"LOGO\": \"/dbt/uploads/logos/adidas.jpg?ts=1669899628\",\n    \"Effective_date\": \"2022-11-30T02:59:00-08:00\",\n    \"check_date\": \"NA\",\n    \"Expire_date\": \"2023-01-23T05:00:00-08:00\",\n    \"img_link\": \"https://coupons.cnet.com/image/eyJrZXkiOiJjbnQvdXBsb2Fkcy9sb2dvcy9hZGlkYXMuanBnIiwib3V0cHV0Rm9ybWF0IjoiIiwiZWRpdHMiOnsicmVzaXplIjp7IndpZHRoIjoxMTcwfX19?ts=1669899628\",\n    \"cmp_desc\": \"NA\",\n    \"cmp_title\": \"adidas Promo Code – Save 60% in January 2023\"\n  },\n  {\n    \"company\": \"adidas\",\n    \"Shop\": \"adidas\",\n    \"LABLE\": \"40%\",\n    \"Desc\": \"Just in: Up to 40% Off Adicolor Collection!\",\n    \"Code\": \"Discount Displayed on Site\",\n    \"Souce\": \"https://www.adidas.com/us\",\n    \"LOGO\": \"/dbt/uploads/logos/adidas.jpg?ts=1669899628\",\n    \"Effective_date\": \"2022-11-14T23:40:00-08:00\",\n    \"check_date\": \"NA\",\n    \"Expire_date\": \"2023-01-02T12:59:00-08:00\",\n    \"img_link\": \"https://coupons.cnet.com/image/eyJrZXkiOiJjbnQvdXBsb2Fkcy9sb2dvcy9hZGlkYXMuanBnIiwib3V0cHV0Rm9ybWF0IjoiIiwiZWRpdHMiOnsicmVzaXplIjp7IndpZHRoIjoxMTcwfX19?ts=1669899628\",\n    \"cmp_desc\": \"NA\",\n    \"cmp_title\": \"adidas Promo Code – Save 60% in January 2023\"\n  },\n  {\n    \"company\": \"adidas\",\n    \"Shop\": \"adidas\",\n    \"LABLE\": \"40%\",\n    \"Desc\": \"Limited Time Only: Up to 40% Off on Terrex Clothing During Winter\",\n    \"Code\": \"Discount Displayed on Site\",\n    \"Souce\": \"https://www.adidas.com/us\",\n    \"LOGO\": \"/dbt/uploads/logos/adidas.jpg?ts=1669899628\",\n    \"Effective_date\": \"2022-11-14T23:41:00-08:00\",\n    \"check_date\": \"NA\",\n    \"Expire_date\": \"2023-01-02T12:59:00-08:00\",\n    \"img_link\": \"https://coupons.cnet.com/image/eyJrZXkiOiJjbnQvdXBsb2Fkcy9sb2dvcy9hZGlkYXMuanBnIiwib3V0cHV0Rm9ybWF0IjoiIiwiZWRpdHMiOnsicmVzaXplIjp7IndpZHRoIjoxMTcwfX19?ts=1669899628\",\n    \"cmp_desc\": \"NA\",\n    \"cmp_title\": \"adidas Promo Code – Save 60% in January 2023\"\n  },\n  {\n    \"company\": \"adidas\",\n    \"Shop\": \"adidas\",\n    \"LABLE\": \"60%\",\n    \"Desc\": \"Just in: Up to 60% off Thousands of Items in the End of Year Sale!\",\n    \"Code\": \"Discount Displayed on Site\",\n    \"Souce\": \"https://www.adidas.com/us\",\n    \"LOGO\": \"/dbt/uploads/logos/adidas.jpg?ts=1669899628\",\n    \"Effective_date\": \"2022-12-12T02:25:00-08:00\",\n    \"check_date\": \"2022-12-27T07:10:28-08:00\",\n    \"Expire_date\": \"2022-12-31T23:59:59-08:00\",\n    \"img_link\": \"https://coupons.cnet.com/image/eyJrZXkiOiJjbnQvdXBsb2Fkcy9sb2dvcy9hZGlkYXMuanBnIiwib3V0cHV0Rm9ybWF0IjoiIiwiZWRpdHMiOnsicmVzaXplIjp7IndpZHRoIjoxMTcwfX19?ts=1669899628\",\n    \"cmp_desc\": \"NA\",\n    \"cmp_title\": \"adidas Promo Code – Save 60% in January 2023\"\n  },\n  {\n    \"company\": \"adidas\",\n    \"Shop\": \"adidas\",\n    \"LABLE\": \"$100\",\n    \"Desc\": \"adidas Promo Code: $100 off\",\n    \"Code\": \"BMSMNOV\",\n    \"Souce\": \"https://www.adidas.com/us\",\n    \"LOGO\": \"/dbt/uploads/logos/adidas.jpg?ts=1669899628\",\n    \"Effective_date\": \"2016-11-09T01:03:00-08:00\",\n    \"check_date\": \"2016-12-01T09:14:21-08:00\",\n    \"Expire_date\": \"2016-11-30T23:59:59-08:00\",\n    \"img_link\": \"https://coupons.cnet.com/image/eyJrZXkiOiJjbnQvdXBsb2Fkcy9sb2dvcy9hZGlkYXMuanBnIiwib3V0cHV0Rm9ybWF0IjoiIiwiZWRpdHMiOnsicmVzaXplIjp7IndpZHRoIjoxMTcwfX19?ts=1669899628\",\n    \"cmp_desc\": \"NA\",\n    \"cmp_title\": \"adidas Promo Code – Save 60% in January 2023\"\n  },\n  {\n    \"company\": \"adidas\",\n    \"Shop\": \"adidas\",\n    \"LABLE\": \"60%\",\n    \"Desc\": \"adidas Coupon: Up to 60% off Sale Items plus Extra 20% with Code\",\n    \"Code\": \"SAVEMORE\",\n    \"Souce\": \"https://www.adidas.com/us\",\n    \"LOGO\": \"/dbt/uploads/logos/adidas.jpg?ts=1669899628\",\n    \"Effective_date\": \"2022-12-21T00:00:00-08:00\",\n    \"check_date\": \"2022-12-21T16:49:48-08:00\",\n    \"Expire_date\": \"2022-12-24T23:59:59-08:00\",\n    \"img_link\": \"https://coupons.cnet.com/image/eyJrZXkiOiJjbnQvdXBsb2Fkcy9sb2dvcy9hZGlkYXMuanBnIiwib3V0cHV0Rm9ybWF0IjoiIiwiZWRpdHMiOnsicmVzaXplIjp7IndpZHRoIjoxMTcwfX19?ts=1669899628\",\n    \"cmp_desc\": \"NA\",\n    \"cmp_title\": \"adidas Promo Code – Save 60% in January 2023\"\n  },\n  {\n    \"company\": \"adidas\",\n    \"Shop\": \"adidas\",\n    \"LABLE\": \"40%\",\n    \"Desc\": \"Save Big: 40% off on Almost Everything\",\n    \"Code\": \"DECEMBER\",\n    \"Souce\": \"https://www.adidas.com/us\",\n    \"LOGO\": \"/dbt/uploads/logos/adidas.jpg?ts=1669899628\",\n    \"Effective_date\": \"2022-12-12T03:24:00-08:00\",\n    \"check_date\": \"2022-12-22T00:39:05-08:00\",\n    \"Expire_date\": \"2022-12-22T00:39:05-08:00\",\n    \"img_link\": \"https://coupons.cnet.com/image/eyJrZXkiOiJjbnQvdXBsb2Fkcy9sb2dvcy9hZGlkYXMuanBnIiwib3V0cHV0Rm9ybWF0IjoiIiwiZWRpdHMiOnsicmVzaXplIjp7IndpZHRoIjoxMTcwfX19?ts=1669899628\",\n    \"cmp_desc\": \"NA\",\n    \"cmp_title\": \"adidas Promo Code – Save 60% in January 2023\"\n  },\n  {\n    \"company\": \"adidas\",\n    \"Shop\": \"adidas\",\n    \"LABLE\": \"40%\",\n    \"Desc\": \"Grab 40% off Full Price And Sale Price Products\",\n    \"Code\": \"DECEMBER\",\n    \"Souce\": \"https://www.adidas.com/us\",\n    \"LOGO\": \"/dbt/uploads/logos/adidas.jpg?ts=1669899628\",\n    \"Effective_date\": \"2022-12-10T00:11:00-08:00\",\n    \"check_date\": \"2022-12-22T00:36:06-08:00\",\n    \"Expire_date\": \"2022-12-22T00:36:06-08:00\",\n    \"img_link\": \"https://coupons.cnet.com/image/eyJrZXkiOiJjbnQvdXBsb2Fkcy9sb2dvcy9hZGlkYXMuanBnIiwib3V0cHV0Rm9ybWF0IjoiIiwiZWRpdHMiOnsicmVzaXplIjp7IndpZHRoIjoxMTcwfX19?ts=1669899628\",\n    \"cmp_desc\": \"NA\",\n    \"cmp_title\": \"adidas Promo Code – Save 60% in January 2023\"\n  },\n  {\n    \"company\": \"adidas\",\n    \"Shop\": \"adidas\",\n    \"LABLE\": \"70%\",\n    \"Desc\": \"Save at adidas with Up to 70% Off\",\n    \"Code\": \"DECEMBER\",\n    \"Souce\": \"https://www.adidas.com/us\",\n    \"LOGO\": \"/dbt/uploads/logos/adidas.jpg?ts=1669899628\",\n    \"Effective_date\": \"2022-12-12T03:23:00-08:00\",\n    \"check_date\": \"2022-12-22T00:35:31-08:00\",\n    \"Expire_date\": \"2022-12-22T00:35:31-08:00\",\n    \"img_link\": \"https://coupons.cnet.com/image/eyJrZXkiOiJjbnQvdXBsb2Fkcy9sb2dvcy9hZGlkYXMuanBnIiwib3V0cHV0Rm9ybWF0IjoiIiwiZWRpdHMiOnsicmVzaXplIjp7IndpZHRoIjoxMTcwfX19?ts=1669899628\",\n    \"cmp_desc\": \"NA\",\n    \"cmp_title\": \"adidas Promo Code – Save 60% in January 2023\"\n  },\n  {\n    \"company\": \"adidas\",\n    \"Shop\": \"adidas\",\n    \"LABLE\": \"$30\",\n    \"Desc\": \"Take advantage: Stocking Stuffers for Under $30\",\n    \"Code\": \"Discount Displayed on Site\",\n    \"Souce\": \"https://www.adidas.com/us\",\n    \"LOGO\": \"/dbt/uploads/logos/adidas.jpg?ts=1669899628\",\n    \"Effective_date\": \"2022-11-29T03:53:00-08:00\",\n    \"check_date\": \"NA\",\n    \"Expire_date\": \"2022-12-21T04:59:00-08:00\",\n    \"img_link\": \"https://coupons.cnet.com/image/eyJrZXkiOiJjbnQvdXBsb2Fkcy9sb2dvcy9hZGlkYXMuanBnIiwib3V0cHV0Rm9ybWF0IjoiIiwiZWRpdHMiOnsicmVzaXplIjp7IndpZHRoIjoxMTcwfX19?ts=1669899628\",\n    \"cmp_desc\": \"NA\",\n    \"cmp_title\": \"adidas Promo Code – Save 60% in January 2023\"\n  },\n  {\n    \"company\": \"adidas\",\n    \"Shop\": \"adidas\",\n    \"LABLE\": \"30%\",\n    \"Desc\": \"Save Big: 30% off Select Sale Styles\",\n    \"Code\": \"SPRING\",\n    \"Souce\": \"https://www.adidas.com/us\",\n    \"LOGO\": \"/dbt/uploads/logos/adidas.jpg?ts=1669899628\",\n    \"Effective_date\": \"2020-03-17T00:00:00-07:00\",\n    \"check_date\": \"2022-07-09T09:48:50-07:00\",\n    \"Expire_date\": \"2022-12-15T23:59:59-08:00\",\n    \"img_link\": \"https://coupons.cnet.com/image/eyJrZXkiOiJjbnQvdXBsb2Fkcy9sb2dvcy9hZGlkYXMuanBnIiwib3V0cHV0Rm9ybWF0IjoiIiwiZWRpdHMiOnsicmVzaXplIjp7IndpZHRoIjoxMTcwfX19?ts=1669899628\",\n    \"cmp_desc\": \"NA\",\n    \"cmp_title\": \"adidas Promo Code – Save 60% in January 2023\"\n  },\n  {\n    \"company\": \"adidas\",\n    \"Shop\": \"adidas\",\n    \"LABLE\": \"40%\",\n    \"Desc\": \"Grab 40% off on Womens Adidas Rich Mnisi Track Jacket\",\n    \"Code\": \"JOY40\",\n    \"Souce\": \"https://www.adidas.com/us\",\n    \"LOGO\": \"/dbt/uploads/logos/adidas.jpg?ts=1669899628\",\n    \"Effective_date\": \"2022-12-14T18:23:00-08:00\",\n    \"check_date\": \"2022-12-15T15:02:57-08:00\",\n    \"Expire_date\": \"2022-12-15T15:02:57-08:00\",\n    \"img_link\": \"https://coupons.cnet.com/image/eyJrZXkiOiJjbnQvdXBsb2Fkcy9sb2dvcy9hZGlkYXMuanBnIiwib3V0cHV0Rm9ybWF0IjoiIiwiZWRpdHMiOnsicmVzaXplIjp7IndpZHRoIjoxMTcwfX19?ts=1669899628\",\n    \"cmp_desc\": \"NA\",\n    \"cmp_title\": \"adidas Promo Code – Save 60% in January 2023\"\n  },\n  {\n    \"company\": \"adidas\",\n    \"Shop\": \"adidas\",\n    \"LABLE\": \"65%\",\n    \"Desc\": \"adidas Coupon: Up to 65% Off Sale Items\",\n    \"Code\": \"EXTRASALE\",\n    \"Souce\": \"https://www.adidas.com/us\",\n    \"LOGO\": \"/dbt/uploads/logos/adidas.jpg?ts=1669899628\",\n    \"Effective_date\": \"2022-11-06T17:16:00-08:00\",\n    \"check_date\": \"2022-11-25T09:21:26-08:00\",\n    \"Expire_date\": \"2022-12-13T04:59:00-08:00\",\n    \"img_link\": \"https://coupons.cnet.com/image/eyJrZXkiOiJjbnQvdXBsb2Fkcy9sb2dvcy9hZGlkYXMuanBnIiwib3V0cHV0Rm9ybWF0IjoiIiwiZWRpdHMiOnsicmVzaXplIjp7IndpZHRoIjoxMTcwfX19?ts=1669899628\",\n    \"cmp_desc\": \"NA\",\n    \"cmp_title\": \"adidas Promo Code – Save 60% in January 2023\"\n  },\n  {\n    \"company\": \"adidas\",\n    \"Shop\": \"adidas\",\n    \"LABLE\": \"30%\",\n    \"Desc\": \"adidas Best Deal of the Season - 30% off Adidas Matching Sets\",\n    \"Code\": \"Discount Displayed on Site\",\n    \"Souce\": \"https://www.adidas.com/us\",\n    \"LOGO\": \"/dbt/uploads/logos/adidas.jpg?ts=1669899628\",\n    \"Effective_date\": \"2022-11-01T00:01:00-07:00\",\n    \"check_date\": \"NA\",\n    \"Expire_date\": \"2022-12-13T04:59:00-08:00\",\n    \"img_link\": \"https://coupons.cnet.com/image/eyJrZXkiOiJjbnQvdXBsb2Fkcy9sb2dvcy9hZGlkYXMuanBnIiwib3V0cHV0Rm9ybWF0IjoiIiwiZWRpdHMiOnsicmVzaXplIjp7IndpZHRoIjoxMTcwfX19?ts=1669899628\",\n    \"cmp_desc\": \"NA\",\n    \"cmp_title\": \"adidas Promo Code – Save 60% in January 2023\"\n  },\n  {\n    \"company\": \"adidas\",\n    \"Shop\": \"adidas\",\n    \"LABLE\": \"40%\",\n    \"Desc\": \"Save at adidas with Extra 40% Off plus Free Shipping on 2022 Women's Styles\",\n    \"Code\": \"DECEMBER\",\n    \"Souce\": \"https://www.adidas.com/us\",\n    \"LOGO\": \"/dbt/uploads/logos/adidas.jpg?ts=1669899628\",\n    \"Effective_date\": \"2022-12-06T17:15:00-08:00\",\n    \"check_date\": \"2022-12-12T12:19:06-08:00\",\n    \"Expire_date\": \"2022-12-12T12:19:06-08:00\",\n    \"img_link\": \"https://coupons.cnet.com/image/eyJrZXkiOiJjbnQvdXBsb2Fkcy9sb2dvcy9hZGlkYXMuanBnIiwib3V0cHV0Rm9ybWF0IjoiIiwiZWRpdHMiOnsicmVzaXplIjp7IndpZHRoIjoxMTcwfX19?ts=1669899628\",\n    \"cmp_desc\": \"NA\",\n    \"cmp_title\": \"adidas Promo Code – Save 60% in January 2023\"\n  },\n  {\n    \"company\": \"adidas\",\n    \"Shop\": \"adidas\",\n    \"LABLE\": \"30%\",\n    \"Desc\": \"adidas Promo Code: 30% off Mens Duramo Slide Sandals\",\n    \"Code\": \"SAVE30\",\n    \"Souce\": \"https://www.adidas.com/us\",\n    \"LOGO\": \"/dbt/uploads/logos/adidas.jpg?ts=1669899628\",\n    \"Effective_date\": \"2020-03-02T05:31:00-08:00\",\n    \"check_date\": \"2022-12-12T12:18:35-08:00\",\n    \"Expire_date\": \"2022-12-12T12:18:35-08:00\",\n    \"img_link\": \"https://coupons.cnet.com/image/eyJrZXkiOiJjbnQvdXBsb2Fkcy9sb2dvcy9hZGlkYXMuanBnIiwib3V0cHV0Rm9ybWF0IjoiIiwiZWRpdHMiOnsicmVzaXplIjp7IndpZHRoIjoxMTcwfX19?ts=1669899628\",\n    \"cmp_desc\": \"NA\",\n    \"cmp_title\": \"adidas Promo Code – Save 60% in January 2023\"\n  },\n  {\n    \"company\": \"adidas\",\n    \"Shop\": \"adidas\",\n    \"LABLE\": \"40%\",\n    \"Desc\": \"Claim 40% off Sitewide with this Promo Code!\",\n    \"Code\": \"DECEMBER\",\n    \"Souce\": \"https://www.adidas.com/us\",\n    \"LOGO\": \"/dbt/uploads/logos/adidas.jpg?ts=1669899628\",\n    \"Effective_date\": \"2022-12-01T00:00:00-08:00\",\n    \"check_date\": \"2022-12-12T12:18:26-08:00\",\n    \"Expire_date\": \"2022-12-12T12:18:26-08:00\",\n    \"img_link\": \"https://coupons.cnet.com/image/eyJrZXkiOiJjbnQvdXBsb2Fkcy9sb2dvcy9hZGlkYXMuanBnIiwib3V0cHV0Rm9ybWF0IjoiIiwiZWRpdHMiOnsicmVzaXplIjp7IndpZHRoIjoxMTcwfX19?ts=1669899628\",\n    \"cmp_desc\": \"NA\",\n    \"cmp_title\": \"adidas Promo Code – Save 60% in January 2023\"\n  },\n  {\n    \"company\": \"adidas\",\n    \"Shop\": \"Academy Sports\",\n    \"LABLE\": \"65%\",\n    \"Desc\": \"65% off Your Purchase at Academy Sports\",\n    \"Code\": \"QUADPAY\",\n    \"Souce\": \"https://www.academy.com/\",\n    \"LOGO\": \"/cnt/uploads/logos/academy-sports.jpg?1606894191\",\n    \"Effective_date\": \"2022-06-21T18:36:00-07:00\",\n    \"check_date\": \"NA\",\n    \"Expire_date\": \"NA\",\n    \"img_link\": \"https://coupons.cnet.com/image/eyJrZXkiOiJjbnQvdXBsb2Fkcy9sb2dvcy9hZGlkYXMuanBnIiwib3V0cHV0Rm9ybWF0IjoiIiwiZWRpdHMiOnsicmVzaXplIjp7IndpZHRoIjoxMTcwfX19?ts=1669899628\",\n    \"cmp_desc\": \"NA\",\n    \"cmp_title\": \"adidas Promo Code – Save 60% in January 2023\"\n  },\n  {\n    \"company\": \"adidas\",\n    \"Shop\": \"NFL Shop\",\n    \"LABLE\": \"25%\",\n    \"Desc\": \"25% off Sitewide at NFL Shop\",\n    \"Code\": \"SCORED\",\n    \"Souce\": \"https://www.nflshop.com/\",\n    \"LOGO\": \"/cnt/uploads/logos/nfl-shop.jpg?1606894191\",\n    \"Effective_date\": \"2022-11-20T12:58:00-08:00\",\n    \"check_date\": \"2022-11-24T09:20:43-08:00\",\n    \"Expire_date\": \"NA\",\n    \"img_link\": \"https://coupons.cnet.com/image/eyJrZXkiOiJjbnQvdXBsb2Fkcy9sb2dvcy9hZGlkYXMuanBnIiwib3V0cHV0Rm9ybWF0IjoiIiwiZWRpdHMiOnsicmVzaXplIjp7IndpZHRoIjoxMTcwfX19?ts=1669899628\",\n    \"cmp_desc\": \"NA\",\n    \"cmp_title\": \"adidas Promo Code – Save 60% in January 2023\"\n  },\n  {\n    \"company\": \"adidas\",\n    \"Shop\": \"Dick's Sporting Goods\",\n    \"LABLE\": \"$20\",\n    \"Desc\": \"$20 off Sitewide at Dick's Sporting Goods\",\n    \"Code\": \"COACH\",\n    \"Souce\": \"https://www.dickssportinggoods.com/\",\n    \"LOGO\": \"/cnt/uploads/logos/dicks-sporting-goods.jpg?1606894191\",\n    \"Effective_date\": \"2021-08-20T05:45:00-07:00\",\n    \"check_date\": \"2021-08-20T15:45:24-07:00\",\n    \"Expire_date\": \"NA\",\n    \"img_link\": \"https://coupons.cnet.com/image/eyJrZXkiOiJjbnQvdXBsb2Fkcy9sb2dvcy9hZGlkYXMuanBnIiwib3V0cHV0Rm9ybWF0IjoiIiwiZWRpdHMiOnsicmVzaXplIjp7IndpZHRoIjoxMTcwfX19?ts=1669899628\",\n    \"cmp_desc\": \"NA\",\n    \"cmp_title\": \"adidas Promo Code – Save 60% in January 2023\"\n  },\n  {\n    \"company\": \"adidas\",\n    \"Shop\": \"DoorDash\",\n    \"LABLE\": \"50%\",\n    \"Desc\": \"Grab 50% off Sitewide\",\n    \"Code\": \"GAME50\",\n    \"Souce\": \"https://www.doordash.com/\",\n    \"LOGO\": \"/cnt/uploads/logos/doordash.jpg?1646158704\",\n    \"Effective_date\": \"2022-11-25T02:48:00-08:00\",\n    \"check_date\": \"2022-12-13T09:18:52-08:00\",\n    \"Expire_date\": \"NA\",\n    \"img_link\": \"https://coupons.cnet.com/image/eyJrZXkiOiJjbnQvdXBsb2Fkcy9sb2dvcy9hZGlkYXMuanBnIiwib3V0cHV0Rm9ybWF0IjoiIiwiZWRpdHMiOnsicmVzaXplIjp7IndpZHRoIjoxMTcwfX19?ts=1669899628\",\n    \"cmp_desc\": \"NA\",\n    \"cmp_title\": \"adidas Promo Code – Save 60% in January 2023\"\n  }\n]"]
