["[\n  {\n    \"company\": \"at-t\",\n    \"Shop\": \"AT&T Fiber\",\n    \"LABLE\": \"$200\",\n    \"Desc\": \"Save at AT&T Fiber with Up to a $200 AT&T Visa Reward Card with AT&T Fiber + Extra $50 Reward Card\",\n    \"Code\": \"EXTRA50\",\n    \"Souce\": \"https://www.att.com/internet/\",\n    \"LOGO\": \"/cnt/uploads/logos/at-t.jpeg?1646928796\",\n    \"Effective_date\": \"2022-11-01T00:01:00-07:00\",\n    \"check_date\": \"NA\",\n    \"Expire_date\": \"NA\",\n    \"img_link\": \"https://coupons.cnet.com/image/eyJrZXkiOiJjbnQvdXBsb2Fkcy9sb2dvcy9hdC10LmpwZWciLCJvdXRwdXRGb3JtYXQiOiIiLCJlZGl0cyI6eyJyZXNpemUiOnsid2lkdGgiOjExNzB9fX0=?1646928796\",\n    \"cmp_desc\": \"AT&T Fiber delivers fast, dependable service. Customers can enjoy quick internet speeds plus thousands of hours of on-demand content including live shows and sports events. AT&T Fiber requires no commitment or annual contract. Choose the TV and internet bundle that suits your needs, and redeem an AT&T Fiber coupon to lower your subscription fee.\",\n    \"cmp_title\": \"AT&T Fiber Promo Code – Save $250 in January 2023\"\n  },\n  {\n    \"company\": \"at-t\",\n    \"Shop\": \"AT&T Fiber\",\n    \"LABLE\": \"$250\",\n    \"Desc\": \"Up to $250 in Reward Cards with AT&T Internet Promo at AT&T Fiber\",\n    \"Code\": \"CONNECTEDCOMMUNITY\",\n    \"Souce\": \"https://www.att.com/internet/\",\n    \"LOGO\": \"/cnt/uploads/logos/at-t.jpeg?1646928796\",\n    \"Effective_date\": \"2022-07-14T22:24:00-07:00\",\n    \"check_date\": \"2022-11-08T09:34:26-08:00\",\n    \"Expire_date\": \"2022-11-08T09:34:26-08:00\",\n    \"img_link\": \"https://coupons.cnet.com/image/eyJrZXkiOiJjbnQvdXBsb2Fkcy9sb2dvcy9hdC10LmpwZWciLCJvdXRwdXRGb3JtYXQiOiIiLCJlZGl0cyI6eyJyZXNpemUiOnsid2lkdGgiOjExNzB9fX0=?1646928796\",\n    \"cmp_desc\": \"AT&T Fiber delivers fast, dependable service. Customers can enjoy quick internet speeds plus thousands of hours of on-demand content including live shows and sports events. AT&T Fiber requires no commitment or annual contract. Choose the TV and internet bundle that suits your needs, and redeem an AT&T Fiber coupon to lower your subscription fee.\",\n    \"cmp_title\": \"AT&T Fiber Promo Code – Save $250 in January 2023\"\n  },\n  {\n    \"company\": \"at-t\",\n    \"Shop\": \"AT&T Fiber\",\n    \"LABLE\": \"NA\",\n    \"Desc\": \"Save at AT&T Fiber - Save More When You Bundle TV & Internet\",\n    \"Code\": \"See Site for Details\",\n    \"Souce\": \"https://www.att.com/internet/\",\n    \"LOGO\": \"/cnt/uploads/logos/at-t.jpeg?1646928796\",\n    \"Effective_date\": \"2022-03-14T08:41:00-07:00\",\n    \"check_date\": \"2022-05-14T07:54:56-07:00\",\n    \"Expire_date\": \"NA\",\n    \"img_link\": \"https://coupons.cnet.com/image/eyJrZXkiOiJjbnQvdXBsb2Fkcy9sb2dvcy9hdC10LmpwZWciLCJvdXRwdXRGb3JtYXQiOiIiLCJlZGl0cyI6eyJyZXNpemUiOnsid2lkdGgiOjExNzB9fX0=?1646928796\",\n    \"cmp_desc\": \"AT&T Fiber delivers fast, dependable service. Customers can enjoy quick internet speeds plus thousands of hours of on-demand content including live shows and sports events. AT&T Fiber requires no commitment or annual contract. Choose the TV and internet bundle that suits your needs, and redeem an AT&T Fiber coupon to lower your subscription fee.\",\n    \"cmp_title\": \"AT&T Fiber Promo Code – Save $250 in January 2023\"\n  },\n  {\n    \"company\": \"at-t\",\n    \"Shop\": \"AT&T Fiber\",\n    \"LABLE\": \"$50\",\n    \"Desc\": \"AT&T Fiber Coupon: Get $50 Reward Card with any Plan Sign-Up\",\n    \"Code\": \"NEWYEAR50\",\n    \"Souce\": \"https://www.att.com/internet/\",\n    \"LOGO\": \"/cnt/uploads/logos/at-t.jpeg?1646928796\",\n    \"Effective_date\": \"2022-05-28T03:02:00-07:00\",\n    \"check_date\": \"NA\",\n    \"Expire_date\": \"NA\",\n    \"img_link\": \"https://coupons.cnet.com/image/eyJrZXkiOiJjbnQvdXBsb2Fkcy9sb2dvcy9hdC10LmpwZWciLCJvdXRwdXRGb3JtYXQiOiIiLCJlZGl0cyI6eyJyZXNpemUiOnsid2lkdGgiOjExNzB9fX0=?1646928796\",\n    \"cmp_desc\": \"AT&T Fiber delivers fast, dependable service. Customers can enjoy quick internet speeds plus thousands of hours of on-demand content including live shows and sports events. AT&T Fiber requires no commitment or annual contract. Choose the TV and internet bundle that suits your needs, and redeem an AT&T Fiber coupon to lower your subscription fee.\",\n    \"cmp_title\": \"AT&T Fiber Promo Code – Save $250 in January 2023\"\n  },\n  {\n    \"company\": \"at-t\",\n    \"Shop\": \"AT&T Fiber\",\n    \"LABLE\": \"$50\",\n    \"Desc\": \"AT&T Fiber Coupon: Free $50 Reward Card with At&T Fiber Packages\",\n    \"Code\": \"HOLIDAY50\",\n    \"Souce\": \"https://www.att.com/internet/\",\n    \"LOGO\": \"/cnt/uploads/logos/at-t.jpeg?1646928796\",\n    \"Effective_date\": \"2020-11-01T00:00:00-07:00\",\n    \"check_date\": \"2021-02-11T04:57:08-08:00\",\n    \"Expire_date\": \"2023-12-31T23:59:00-08:00\",\n    \"img_link\": \"https://coupons.cnet.com/image/eyJrZXkiOiJjbnQvdXBsb2Fkcy9sb2dvcy9hdC10LmpwZWciLCJvdXRwdXRGb3JtYXQiOiIiLCJlZGl0cyI6eyJyZXNpemUiOnsid2lkdGgiOjExNzB9fX0=?1646928796\",\n    \"cmp_desc\": \"AT&T Fiber delivers fast, dependable service. Customers can enjoy quick internet speeds plus thousands of hours of on-demand content including live shows and sports events. AT&T Fiber requires no commitment or annual contract. Choose the TV and internet bundle that suits your needs, and redeem an AT&T Fiber coupon to lower your subscription fee.\",\n    \"cmp_title\": \"AT&T Fiber Promo Code – Save $250 in January 2023\"\n  },\n  {\n    \"company\": \"at-t\",\n    \"Shop\": \"AT&T Fiber\",\n    \"LABLE\": \"$200\",\n    \"Desc\": \"Save at AT&T Fiber with Up to $200 AT&T Visa Reward Card with AT&T Fiber + Extra $50 Reward Card this Cyber Monday\",\n    \"Code\": \"FALL50\",\n    \"Souce\": \"https://www.att.com/internet/\",\n    \"LOGO\": \"/cnt/uploads/logos/at-t.jpeg?1646928796\",\n    \"Effective_date\": \"2022-11-01T00:01:00-07:00\",\n    \"check_date\": \"NA\",\n    \"Expire_date\": \"2022-11-30T23:59:59-08:00\",\n    \"img_link\": \"https://coupons.cnet.com/image/eyJrZXkiOiJjbnQvdXBsb2Fkcy9sb2dvcy9hdC10LmpwZWciLCJvdXRwdXRGb3JtYXQiOiIiLCJlZGl0cyI6eyJyZXNpemUiOnsid2lkdGgiOjExNzB9fX0=?1646928796\",\n    \"cmp_desc\": \"AT&T Fiber delivers fast, dependable service. Customers can enjoy quick internet speeds plus thousands of hours of on-demand content including live shows and sports events. AT&T Fiber requires no commitment or annual contract. Choose the TV and internet bundle that suits your needs, and redeem an AT&T Fiber coupon to lower your subscription fee.\",\n    \"cmp_title\": \"AT&T Fiber Promo Code – Save $250 in January 2023\"\n  },\n  {\n    \"company\": \"at-t\",\n    \"Shop\": \"AT&T Fiber\",\n    \"LABLE\": \"$50\",\n    \"Desc\": \"AT&T Fiber Promo Code: $50 off\",\n    \"Code\": \"HOLIDAY50\",\n    \"Souce\": \"https://www.att.com/internet/\",\n    \"LOGO\": \"/cnt/uploads/logos/at-t.jpeg?1646928796\",\n    \"Effective_date\": \"2022-10-29T07:56:00-07:00\",\n    \"check_date\": \"NA\",\n    \"Expire_date\": \"2023-01-05T23:59:59-08:00\",\n    \"img_link\": \"https://coupons.cnet.com/image/eyJrZXkiOiJjbnQvdXBsb2Fkcy9sb2dvcy9hdC10LmpwZWciLCJvdXRwdXRGb3JtYXQiOiIiLCJlZGl0cyI6eyJyZXNpemUiOnsid2lkdGgiOjExNzB9fX0=?1646928796\",\n    \"cmp_desc\": \"AT&T Fiber delivers fast, dependable service. Customers can enjoy quick internet speeds plus thousands of hours of on-demand content including live shows and sports events. AT&T Fiber requires no commitment or annual contract. Choose the TV and internet bundle that suits your needs, and redeem an AT&T Fiber coupon to lower your subscription fee.\",\n    \"cmp_title\": \"AT&T Fiber Promo Code – Save $250 in January 2023\"\n  },\n  {\n    \"company\": \"at-t\",\n    \"Shop\": \"AT&T Fiber\",\n    \"LABLE\": \"$250\",\n    \"Desc\": \"AT&T Fiber Offer - Earn $250 Reward Card\",\n    \"Code\": \"Discount Displayed on Site\",\n    \"Souce\": \"https://www.att.com/internet/\",\n    \"LOGO\": \"/cnt/uploads/logos/at-t.jpeg?1646928796\",\n    \"Effective_date\": \"2022-08-08T23:18:00-07:00\",\n    \"check_date\": \"NA\",\n    \"Expire_date\": \"2022-10-09T23:59:59-07:00\",\n    \"img_link\": \"https://coupons.cnet.com/image/eyJrZXkiOiJjbnQvdXBsb2Fkcy9sb2dvcy9hdC10LmpwZWciLCJvdXRwdXRGb3JtYXQiOiIiLCJlZGl0cyI6eyJyZXNpemUiOnsid2lkdGgiOjExNzB9fX0=?1646928796\",\n    \"cmp_desc\": \"AT&T Fiber delivers fast, dependable service. Customers can enjoy quick internet speeds plus thousands of hours of on-demand content including live shows and sports events. AT&T Fiber requires no commitment or annual contract. Choose the TV and internet bundle that suits your needs, and redeem an AT&T Fiber coupon to lower your subscription fee.\",\n    \"cmp_title\": \"AT&T Fiber Promo Code – Save $250 in January 2023\"\n  },\n  {\n    \"company\": \"at-t\",\n    \"Shop\": \"AT&T Fiber\",\n    \"LABLE\": \"$50\",\n    \"Desc\": \"Earn Extra $50 Reward Card on Fiber Internet at AT&T Fiber\",\n    \"Code\": \"SUMMER50\",\n    \"Souce\": \"https://www.att.com/internet/\",\n    \"LOGO\": \"/cnt/uploads/logos/at-t.jpeg?1646928796\",\n    \"Effective_date\": \"2021-06-01T03:40:00-07:00\",\n    \"check_date\": \"NA\",\n    \"Expire_date\": \"2022-09-30T23:59:59-07:00\",\n    \"img_link\": \"https://coupons.cnet.com/image/eyJrZXkiOiJjbnQvdXBsb2Fkcy9sb2dvcy9hdC10LmpwZWciLCJvdXRwdXRGb3JtYXQiOiIiLCJlZGl0cyI6eyJyZXNpemUiOnsid2lkdGgiOjExNzB9fX0=?1646928796\",\n    \"cmp_desc\": \"AT&T Fiber delivers fast, dependable service. Customers can enjoy quick internet speeds plus thousands of hours of on-demand content including live shows and sports events. AT&T Fiber requires no commitment or annual contract. Choose the TV and internet bundle that suits your needs, and redeem an AT&T Fiber coupon to lower your subscription fee.\",\n    \"cmp_title\": \"AT&T Fiber Promo Code – Save $250 in January 2023\"\n  },\n  {\n    \"company\": \"at-t\",\n    \"Shop\": \"AT&T Fiber\",\n    \"LABLE\": \"$100\",\n    \"Desc\": \"Save at AT&T Fiber with Free $100 Reward Card with Subscription Orders\",\n    \"Code\": \"XTRA100\",\n    \"Souce\": \"https://www.att.com/internet/\",\n    \"LOGO\": \"/cnt/uploads/logos/at-t.jpeg?1646928796\",\n    \"Effective_date\": \"2022-05-31T21:00:00-07:00\",\n    \"check_date\": \"NA\",\n    \"Expire_date\": \"2022-08-31T23:59:59-07:00\",\n    \"img_link\": \"https://coupons.cnet.com/image/eyJrZXkiOiJjbnQvdXBsb2Fkcy9sb2dvcy9hdC10LmpwZWciLCJvdXRwdXRGb3JtYXQiOiIiLCJlZGl0cyI6eyJyZXNpemUiOnsid2lkdGgiOjExNzB9fX0=?1646928796\",\n    \"cmp_desc\": \"AT&T Fiber delivers fast, dependable service. Customers can enjoy quick internet speeds plus thousands of hours of on-demand content including live shows and sports events. AT&T Fiber requires no commitment or annual contract. Choose the TV and internet bundle that suits your needs, and redeem an AT&T Fiber coupon to lower your subscription fee.\",\n    \"cmp_title\": \"AT&T Fiber Promo Code – Save $250 in January 2023\"\n  },\n  {\n    \"company\": \"at-t\",\n    \"Shop\": \"AT&T Fiber\",\n    \"LABLE\": \"NA\",\n    \"Desc\": \"Take advantage: Free Express Shipping\",\n    \"Code\": \"Discount Applied at Checkout\",\n    \"Souce\": \"https://www.att.com/internet/\",\n    \"LOGO\": \"/cnt/uploads/logos/at-t.jpeg?1646928796\",\n    \"Effective_date\": \"2020-06-25T10:59:00-07:00\",\n    \"check_date\": \"2022-06-06T00:56:31-07:00\",\n    \"Expire_date\": \"2022-06-06T00:56:31-07:00\",\n    \"img_link\": \"https://coupons.cnet.com/image/eyJrZXkiOiJjbnQvdXBsb2Fkcy9sb2dvcy9hdC10LmpwZWciLCJvdXRwdXRGb3JtYXQiOiIiLCJlZGl0cyI6eyJyZXNpemUiOnsid2lkdGgiOjExNzB9fX0=?1646928796\",\n    \"cmp_desc\": \"AT&T Fiber delivers fast, dependable service. Customers can enjoy quick internet speeds plus thousands of hours of on-demand content including live shows and sports events. AT&T Fiber requires no commitment or annual contract. Choose the TV and internet bundle that suits your needs, and redeem an AT&T Fiber coupon to lower your subscription fee.\",\n    \"cmp_title\": \"AT&T Fiber Promo Code – Save $250 in January 2023\"\n  },\n  {\n    \"company\": \"at-t\",\n    \"Shop\": \"AT&T Fiber\",\n    \"LABLE\": \"$200\",\n    \"Desc\": \"Seasonal Savings: Get $200 AT&T Visa® Reward Card with qualifying AT&T Internet\",\n    \"Code\": \"Discount Displayed on Site\",\n    \"Souce\": \"https://www.att.com/internet/\",\n    \"LOGO\": \"/cnt/uploads/logos/at-t.jpeg?1646928796\",\n    \"Effective_date\": \"2022-04-01T08:33:00-07:00\",\n    \"check_date\": \"2022-06-06T00:53:42-07:00\",\n    \"Expire_date\": \"2022-06-06T00:53:42-07:00\",\n    \"img_link\": \"https://coupons.cnet.com/image/eyJrZXkiOiJjbnQvdXBsb2Fkcy9sb2dvcy9hdC10LmpwZWciLCJvdXRwdXRGb3JtYXQiOiIiLCJlZGl0cyI6eyJyZXNpemUiOnsid2lkdGgiOjExNzB9fX0=?1646928796\",\n    \"cmp_desc\": \"AT&T Fiber delivers fast, dependable service. Customers can enjoy quick internet speeds plus thousands of hours of on-demand content including live shows and sports events. AT&T Fiber requires no commitment or annual contract. Choose the TV and internet bundle that suits your needs, and redeem an AT&T Fiber coupon to lower your subscription fee.\",\n    \"cmp_title\": \"AT&T Fiber Promo Code – Save $250 in January 2023\"\n  },\n  {\n    \"company\": \"at-t\",\n    \"Shop\": \"AT&T Fiber\",\n    \"LABLE\": \"$50\",\n    \"Desc\": \"AT&T Fiber Coupon: Order AT&T Fiber and Get an Extra $50 Reward Card when you order AT&T Fiber\",\n    \"Code\": \"SPRING50\",\n    \"Souce\": \"https://www.att.com/internet/\",\n    \"LOGO\": \"/cnt/uploads/logos/at-t.jpeg?1646928796\",\n    \"Effective_date\": \"2021-03-12T01:44:00-08:00\",\n    \"check_date\": \"2022-03-11T21:55:04-08:00\",\n    \"Expire_date\": \"2022-05-31T23:59:59-07:00\",\n    \"img_link\": \"https://coupons.cnet.com/image/eyJrZXkiOiJjbnQvdXBsb2Fkcy9sb2dvcy9hdC10LmpwZWciLCJvdXRwdXRGb3JtYXQiOiIiLCJlZGl0cyI6eyJyZXNpemUiOnsid2lkdGgiOjExNzB9fX0=?1646928796\",\n    \"cmp_desc\": \"AT&T Fiber delivers fast, dependable service. Customers can enjoy quick internet speeds plus thousands of hours of on-demand content including live shows and sports events. AT&T Fiber requires no commitment or annual contract. Choose the TV and internet bundle that suits your needs, and redeem an AT&T Fiber coupon to lower your subscription fee.\",\n    \"cmp_title\": \"AT&T Fiber Promo Code – Save $250 in January 2023\"\n  },\n  {\n    \"company\": \"at-t\",\n    \"Shop\": \"AT&T Fiber\",\n    \"LABLE\": \"NA\",\n    \"Desc\": \"Limited Time Only: Get 6 Months of Stadia Pro on Us\",\n    \"Code\": \"See Site for Details\",\n    \"Souce\": \"https://www.att.com/internet/\",\n    \"LOGO\": \"/cnt/uploads/logos/at-t.jpeg?1646928796\",\n    \"Effective_date\": \"2022-03-14T08:45:00-07:00\",\n    \"check_date\": \"2022-03-14T16:47:52-07:00\",\n    \"Expire_date\": \"2022-05-27T23:59:59-07:00\",\n    \"img_link\": \"https://coupons.cnet.com/image/eyJrZXkiOiJjbnQvdXBsb2Fkcy9sb2dvcy9hdC10LmpwZWciLCJvdXRwdXRGb3JtYXQiOiIiLCJlZGl0cyI6eyJyZXNpemUiOnsid2lkdGgiOjExNzB9fX0=?1646928796\",\n    \"cmp_desc\": \"AT&T Fiber delivers fast, dependable service. Customers can enjoy quick internet speeds plus thousands of hours of on-demand content including live shows and sports events. AT&T Fiber requires no commitment or annual contract. Choose the TV and internet bundle that suits your needs, and redeem an AT&T Fiber coupon to lower your subscription fee.\",\n    \"cmp_title\": \"AT&T Fiber Promo Code – Save $250 in January 2023\"\n  },\n  {\n    \"company\": \"at-t\",\n    \"Shop\": \"AT&T Fiber\",\n    \"LABLE\": \"$300\",\n    \"Desc\": \"Seasonal Savings: Learn How to Get a $300 Reward Card when You Order AT&T Internet\",\n    \"Code\": \"See Site for Details\",\n    \"Souce\": \"https://www.att.com/internet/\",\n    \"LOGO\": \"/cnt/uploads/logos/at-t.jpeg?1646928796\",\n    \"Effective_date\": \"2022-03-11T01:51:00-08:00\",\n    \"check_date\": \"2022-03-14T16:48:01-07:00\",\n    \"Expire_date\": \"2022-03-31T23:59:59-07:00\",\n    \"img_link\": \"https://coupons.cnet.com/image/eyJrZXkiOiJjbnQvdXBsb2Fkcy9sb2dvcy9hdC10LmpwZWciLCJvdXRwdXRGb3JtYXQiOiIiLCJlZGl0cyI6eyJyZXNpemUiOnsid2lkdGgiOjExNzB9fX0=?1646928796\",\n    \"cmp_desc\": \"AT&T Fiber delivers fast, dependable service. Customers can enjoy quick internet speeds plus thousands of hours of on-demand content including live shows and sports events. AT&T Fiber requires no commitment or annual contract. Choose the TV and internet bundle that suits your needs, and redeem an AT&T Fiber coupon to lower your subscription fee.\",\n    \"cmp_title\": \"AT&T Fiber Promo Code – Save $250 in January 2023\"\n  },\n  {\n    \"company\": \"at-t\",\n    \"Shop\": \"AT&T Fiber\",\n    \"LABLE\": \"$55\",\n    \"Desc\": \"Just in: AT&T Internet $55/mo. for 12 Mos. + $300 Reward Card !\",\n    \"Code\": \"See Site for Details\",\n    \"Souce\": \"https://www.att.com/internet/\",\n    \"LOGO\": \"/cnt/uploads/logos/at-t.jpeg?1646928796\",\n    \"Effective_date\": \"2022-03-14T08:38:00-07:00\",\n    \"check_date\": \"2022-03-14T16:47:49-07:00\",\n    \"Expire_date\": \"2022-03-31T23:59:59-07:00\",\n    \"img_link\": \"https://coupons.cnet.com/image/eyJrZXkiOiJjbnQvdXBsb2Fkcy9sb2dvcy9hdC10LmpwZWciLCJvdXRwdXRGb3JtYXQiOiIiLCJlZGl0cyI6eyJyZXNpemUiOnsid2lkdGgiOjExNzB9fX0=?1646928796\",\n    \"cmp_desc\": \"AT&T Fiber delivers fast, dependable service. Customers can enjoy quick internet speeds plus thousands of hours of on-demand content including live shows and sports events. AT&T Fiber requires no commitment or annual contract. Choose the TV and internet bundle that suits your needs, and redeem an AT&T Fiber coupon to lower your subscription fee.\",\n    \"cmp_title\": \"AT&T Fiber Promo Code – Save $250 in January 2023\"\n  },\n  {\n    \"company\": \"at-t\",\n    \"Shop\": \"AT&T Fiber\",\n    \"LABLE\": \"$50\",\n    \"Desc\": \"AT&T Fiber Coupon: Free $50 Reward Card with AT&T Fiber Internet Order\",\n    \"Code\": \"NEWYEAR50\",\n    \"Souce\": \"https://www.att.com/internet/\",\n    \"LOGO\": \"/cnt/uploads/logos/at-t.jpeg?1646928796\",\n    \"Effective_date\": \"2021-01-07T04:24:00-08:00\",\n    \"check_date\": \"2022-03-11T21:56:06-08:00\",\n    \"Expire_date\": \"2022-03-11T21:56:06-08:00\",\n    \"img_link\": \"https://coupons.cnet.com/image/eyJrZXkiOiJjbnQvdXBsb2Fkcy9sb2dvcy9hdC10LmpwZWciLCJvdXRwdXRGb3JtYXQiOiIiLCJlZGl0cyI6eyJyZXNpemUiOnsid2lkdGgiOjExNzB9fX0=?1646928796\",\n    \"cmp_desc\": \"AT&T Fiber delivers fast, dependable service. Customers can enjoy quick internet speeds plus thousands of hours of on-demand content including live shows and sports events. AT&T Fiber requires no commitment or annual contract. Choose the TV and internet bundle that suits your needs, and redeem an AT&T Fiber coupon to lower your subscription fee.\",\n    \"cmp_title\": \"AT&T Fiber Promo Code – Save $250 in January 2023\"\n  },\n  {\n    \"company\": \"at-t\",\n    \"Shop\": \"AT&T Fiber\",\n    \"LABLE\": \"$50\",\n    \"Desc\": \"Save at AT&T Fiber with $50 Reward Card when you Order AT&T Fiber\",\n    \"Code\": \"HOLIDAY50\",\n    \"Souce\": \"https://www.att.com/internet/\",\n    \"LOGO\": \"/cnt/uploads/logos/at-t.jpeg?1646928796\",\n    \"Effective_date\": \"2021-11-10T01:18:00-08:00\",\n    \"check_date\": \"NA\",\n    \"Expire_date\": \"2021-12-31T23:59:59-08:00\",\n    \"img_link\": \"https://coupons.cnet.com/image/eyJrZXkiOiJjbnQvdXBsb2Fkcy9sb2dvcy9hdC10LmpwZWciLCJvdXRwdXRGb3JtYXQiOiIiLCJlZGl0cyI6eyJyZXNpemUiOnsid2lkdGgiOjExNzB9fX0=?1646928796\",\n    \"cmp_desc\": \"AT&T Fiber delivers fast, dependable service. Customers can enjoy quick internet speeds plus thousands of hours of on-demand content including live shows and sports events. AT&T Fiber requires no commitment or annual contract. Choose the TV and internet bundle that suits your needs, and redeem an AT&T Fiber coupon to lower your subscription fee.\",\n    \"cmp_title\": \"AT&T Fiber Promo Code – Save $250 in January 2023\"\n  },\n  {\n    \"company\": \"at-t\",\n    \"Shop\": \"AT&T Fiber\",\n    \"LABLE\": \"NA\",\n    \"Desc\": \"AT&T Fiber Coupon: Cyber Monday Deal: Order AT&T Fiber and get a $200 reward card or a smart home bundle\",\n    \"Code\": \"GET200\",\n    \"Souce\": \"https://www.att.com/internet/\",\n    \"LOGO\": \"/cnt/uploads/logos/at-t.jpeg?1646928796\",\n    \"Effective_date\": \"2021-11-24T10:20:00-08:00\",\n    \"check_date\": \"NA\",\n    \"Expire_date\": \"2021-12-01T23:59:59-08:00\",\n    \"img_link\": \"https://coupons.cnet.com/image/eyJrZXkiOiJjbnQvdXBsb2Fkcy9sb2dvcy9hdC10LmpwZWciLCJvdXRwdXRGb3JtYXQiOiIiLCJlZGl0cyI6eyJyZXNpemUiOnsid2lkdGgiOjExNzB9fX0=?1646928796\",\n    \"cmp_desc\": \"AT&T Fiber delivers fast, dependable service. Customers can enjoy quick internet speeds plus thousands of hours of on-demand content including live shows and sports events. AT&T Fiber requires no commitment or annual contract. Choose the TV and internet bundle that suits your needs, and redeem an AT&T Fiber coupon to lower your subscription fee.\",\n    \"cmp_title\": \"AT&T Fiber Promo Code – Save $250 in January 2023\"\n  },\n  {\n    \"company\": \"at-t\",\n    \"Shop\": \"AT&T Fiber\",\n    \"LABLE\": \"$1000\",\n    \"Desc\": \"AT&T Fiber Offer - Up to $1000 off iPhone 13 Pro Max\",\n    \"Code\": \"Discount Displayed on Site\",\n    \"Souce\": \"https://www.att.com/internet/\",\n    \"LOGO\": \"/cnt/uploads/logos/at-t.jpeg?1646928796\",\n    \"Effective_date\": \"2021-11-26T04:02:00-08:00\",\n    \"check_date\": \"NA\",\n    \"Expire_date\": \"2021-11-29T23:59:59-08:00\",\n    \"img_link\": \"https://coupons.cnet.com/image/eyJrZXkiOiJjbnQvdXBsb2Fkcy9sb2dvcy9hdC10LmpwZWciLCJvdXRwdXRGb3JtYXQiOiIiLCJlZGl0cyI6eyJyZXNpemUiOnsid2lkdGgiOjExNzB9fX0=?1646928796\",\n    \"cmp_desc\": \"AT&T Fiber delivers fast, dependable service. Customers can enjoy quick internet speeds plus thousands of hours of on-demand content including live shows and sports events. AT&T Fiber requires no commitment or annual contract. Choose the TV and internet bundle that suits your needs, and redeem an AT&T Fiber coupon to lower your subscription fee.\",\n    \"cmp_title\": \"AT&T Fiber Promo Code – Save $250 in January 2023\"\n  },\n  {\n    \"company\": \"at-t\",\n    \"Shop\": \"DoorDash\",\n    \"LABLE\": \"50%\",\n    \"Desc\": \"Grab 50% off Sitewide\",\n    \"Code\": \"GAME50\",\n    \"Souce\": \"https://www.doordash.com/\",\n    \"LOGO\": \"/cnt/uploads/logos/doordash.jpg?1646158704\",\n    \"Effective_date\": \"2022-11-25T02:48:00-08:00\",\n    \"check_date\": \"2022-12-13T09:18:52-08:00\",\n    \"Expire_date\": \"NA\",\n    \"img_link\": \"https://coupons.cnet.com/image/eyJrZXkiOiJjbnQvdXBsb2Fkcy9sb2dvcy9hdC10LmpwZWciLCJvdXRwdXRGb3JtYXQiOiIiLCJlZGl0cyI6eyJyZXNpemUiOnsid2lkdGgiOjExNzB9fX0=?1646928796\",\n    \"cmp_desc\": \"AT&T Fiber delivers fast, dependable service. Customers can enjoy quick internet speeds plus thousands of hours of on-demand content including live shows and sports events. AT&T Fiber requires no commitment or annual contract. Choose the TV and internet bundle that suits your needs, and redeem an AT&T Fiber coupon to lower your subscription fee.\",\n    \"cmp_title\": \"AT&T Fiber Promo Code – Save $250 in January 2023\"\n  },\n  {\n    \"company\": \"at-t\",\n    \"Shop\": \"Uber\",\n    \"LABLE\": \"$18\",\n    \"Desc\": \"Top Coupon: $18 off Your First 6 Rides\",\n    \"Code\": \"NEWRIDER18\",\n    \"Souce\": \"https://www.uber.com/\",\n    \"LOGO\": \"/cnt/uploads/logos/uber.jpg?1606894191\",\n    \"Effective_date\": \"2019-09-16T06:31:00-07:00\",\n    \"check_date\": \"2019-10-01T10:10:03-07:00\",\n    \"Expire_date\": \"NA\",\n    \"img_link\": \"https://coupons.cnet.com/image/eyJrZXkiOiJjbnQvdXBsb2Fkcy9sb2dvcy9hdC10LmpwZWciLCJvdXRwdXRGb3JtYXQiOiIiLCJlZGl0cyI6eyJyZXNpemUiOnsid2lkdGgiOjExNzB9fX0=?1646928796\",\n    \"cmp_desc\": \"AT&T Fiber delivers fast, dependable service. Customers can enjoy quick internet speeds plus thousands of hours of on-demand content including live shows and sports events. AT&T Fiber requires no commitment or annual contract. Choose the TV and internet bundle that suits your needs, and redeem an AT&T Fiber coupon to lower your subscription fee.\",\n    \"cmp_title\": \"AT&T Fiber Promo Code – Save $250 in January 2023\"\n  },\n  {\n    \"company\": \"at-t\",\n    \"Shop\": \"H&M\",\n    \"LABLE\": \"20%\",\n    \"Desc\": \"H&M Promo Code: 20% off Sitewide\",\n    \"Code\": \"4224\",\n    \"Souce\": \"https://www2.hm.com/en_us/index.html\",\n    \"LOGO\": \"/cnt/uploads/logos/h-m.jpg?1606894191\",\n    \"Effective_date\": \"2022-12-26T21:41:00-08:00\",\n    \"check_date\": \"NA\",\n    \"Expire_date\": \"NA\",\n    \"img_link\": \"https://coupons.cnet.com/image/eyJrZXkiOiJjbnQvdXBsb2Fkcy9sb2dvcy9hdC10LmpwZWciLCJvdXRwdXRGb3JtYXQiOiIiLCJlZGl0cyI6eyJyZXNpemUiOnsid2lkdGgiOjExNzB9fX0=?1646928796\",\n    \"cmp_desc\": \"AT&T Fiber delivers fast, dependable service. Customers can enjoy quick internet speeds plus thousands of hours of on-demand content including live shows and sports events. AT&T Fiber requires no commitment or annual contract. Choose the TV and internet bundle that suits your needs, and redeem an AT&T Fiber coupon to lower your subscription fee.\",\n    \"cmp_title\": \"AT&T Fiber Promo Code – Save $250 in January 2023\"\n  },\n  {\n    \"company\": \"at-t\",\n    \"Shop\": \"Pizza Hut\",\n    \"LABLE\": \"50%\",\n    \"Desc\": \"Up to 50% Off from Select Locations at Pizza Hut\",\n    \"Code\": \"LIONSWIN\",\n    \"Souce\": \"https://www.pizzahut.com/\",\n    \"LOGO\": \"/cnt/uploads/logos/pizza-hut.jpg?1606894191\",\n    \"Effective_date\": \"2022-06-18T02:52:00-07:00\",\n    \"check_date\": \"2022-12-20T06:50:50-08:00\",\n    \"Expire_date\": \"NA\",\n    \"img_link\": \"https://coupons.cnet.com/image/eyJrZXkiOiJjbnQvdXBsb2Fkcy9sb2dvcy9hdC10LmpwZWciLCJvdXRwdXRGb3JtYXQiOiIiLCJlZGl0cyI6eyJyZXNpemUiOnsid2lkdGgiOjExNzB9fX0=?1646928796\",\n    \"cmp_desc\": \"AT&T Fiber delivers fast, dependable service. Customers can enjoy quick internet speeds plus thousands of hours of on-demand content including live shows and sports events. AT&T Fiber requires no commitment or annual contract. Choose the TV and internet bundle that suits your needs, and redeem an AT&T Fiber coupon to lower your subscription fee.\",\n    \"cmp_title\": \"AT&T Fiber Promo Code – Save $250 in January 2023\"\n  }\n]"]
