["[\n  {\n    \"company\": \"athletic-greens\",\n    \"Shop\": \"Athletic Greens\",\n    \"LABLE\": \"NA\",\n    \"Desc\": \"Save at Athletic Greens with Free Gift\",\n    \"Code\": \"LEX\",\n    \"Souce\": \"https://athleticgreens.com/\",\n    \"LOGO\": \"/cnt/uploads/logos/athletic-greens.jpg?1646917217\",\n    \"Effective_date\": \"2022-09-11T07:03:00-07:00\",\n    \"check_date\": \"2022-12-13T06:30:57-08:00\",\n    \"Expire_date\": \"NA\",\n    \"img_link\": \"https://coupons.cnet.com/image/eyJrZXkiOiJjbnQvdXBsb2Fkcy9sb2dvcy9hdGhsZXRpYy1ncmVlbnMuanBnIiwib3V0cHV0Rm9ybWF0IjoiIiwiZWRpdHMiOnsicmVzaXplIjp7IndpZHRoIjoxMTcwfX19?1646917217\",\n    \"cmp_desc\": \"NA\",\n    \"cmp_title\": \"Athletic Greens Coupons in January 2023\"\n  },\n  {\n    \"company\": \"athletic-greens\",\n    \"Shop\": \"Athletic Greens\",\n    \"LABLE\": \"NA\",\n    \"Desc\": \"Free Gift with any Purchase at Athletic Greens\",\n    \"Code\": \"KATS\",\n    \"Souce\": \"https://athleticgreens.com/\",\n    \"LOGO\": \"/cnt/uploads/logos/athletic-greens.jpg?1646917217\",\n    \"Effective_date\": \"2022-03-13T06:27:00-07:00\",\n    \"check_date\": \"2022-05-13T00:21:24-07:00\",\n    \"Expire_date\": \"2022-05-13T00:21:24-07:00\",\n    \"img_link\": \"https://coupons.cnet.com/image/eyJrZXkiOiJjbnQvdXBsb2Fkcy9sb2dvcy9hdGhsZXRpYy1ncmVlbnMuanBnIiwib3V0cHV0Rm9ybWF0IjoiIiwiZWRpdHMiOnsicmVzaXplIjp7IndpZHRoIjoxMTcwfX19?1646917217\",\n    \"cmp_desc\": \"NA\",\n    \"cmp_title\": \"Athletic Greens Coupons in January 2023\"\n  },\n  {\n    \"company\": \"athletic-greens\",\n    \"Shop\": \"Athletic Greens\",\n    \"LABLE\": \"NA\",\n    \"Desc\": \"Save at Athletic Greens with Free Gift\",\n    \"Code\": \"ROGAN\",\n    \"Souce\": \"https://athleticgreens.com/\",\n    \"LOGO\": \"/cnt/uploads/logos/athletic-greens.jpg?1646917217\",\n    \"Effective_date\": \"2022-09-11T07:03:00-07:00\",\n    \"check_date\": \"2022-12-01T11:50:49-08:00\",\n    \"Expire_date\": \"NA\",\n    \"img_link\": \"https://coupons.cnet.com/image/eyJrZXkiOiJjbnQvdXBsb2Fkcy9sb2dvcy9hdGhsZXRpYy1ncmVlbnMuanBnIiwib3V0cHV0Rm9ybWF0IjoiIiwiZWRpdHMiOnsicmVzaXplIjp7IndpZHRoIjoxMTcwfX19?1646917217\",\n    \"cmp_desc\": \"NA\",\n    \"cmp_title\": \"Athletic Greens Coupons in January 2023\"\n  },\n  {\n    \"company\": \"athletic-greens\",\n    \"Shop\": \"Athletic Greens\",\n    \"LABLE\": \"NA\",\n    \"Desc\": \"Free Gift at Athletic Greens\",\n    \"Code\": \"KATS\",\n    \"Souce\": \"https://athleticgreens.com/\",\n    \"LOGO\": \"/cnt/uploads/logos/athletic-greens.jpg?1646917217\",\n    \"Effective_date\": \"2022-09-11T07:03:00-07:00\",\n    \"check_date\": \"2022-12-01T11:51:39-08:00\",\n    \"Expire_date\": \"NA\",\n    \"img_link\": \"https://coupons.cnet.com/image/eyJrZXkiOiJjbnQvdXBsb2Fkcy9sb2dvcy9hdGhsZXRpYy1ncmVlbnMuanBnIiwib3V0cHV0Rm9ybWF0IjoiIiwiZWRpdHMiOnsicmVzaXplIjp7IndpZHRoIjoxMTcwfX19?1646917217\",\n    \"cmp_desc\": \"NA\",\n    \"cmp_title\": \"Athletic Greens Coupons in January 2023\"\n  },\n  {\n    \"company\": \"athletic-greens\",\n    \"Shop\": \"Athletic Greens\",\n    \"LABLE\": \"NA\",\n    \"Desc\": \"Athletic Greens Offer - 90 Day Money-Back Guarantee\",\n    \"Code\": \"See Site for Details\",\n    \"Souce\": \"https://athleticgreens.com/\",\n    \"LOGO\": \"/cnt/uploads/logos/athletic-greens.jpg?1646917217\",\n    \"Effective_date\": \"2022-03-11T02:53:00-08:00\",\n    \"check_date\": \"2022-11-29T15:02:29-08:00\",\n    \"Expire_date\": \"NA\",\n    \"img_link\": \"https://coupons.cnet.com/image/eyJrZXkiOiJjbnQvdXBsb2Fkcy9sb2dvcy9hdGhsZXRpYy1ncmVlbnMuanBnIiwib3V0cHV0Rm9ybWF0IjoiIiwiZWRpdHMiOnsicmVzaXplIjp7IndpZHRoIjoxMTcwfX19?1646917217\",\n    \"cmp_desc\": \"NA\",\n    \"cmp_title\": \"Athletic Greens Coupons in January 2023\"\n  },\n  {\n    \"company\": \"athletic-greens\",\n    \"Shop\": \"Athletic Greens\",\n    \"LABLE\": \"$49\",\n    \"Desc\": \"Athletic Greens is Offering $49 off Double Subscriptions\",\n    \"Code\": \"Discount Displayed on Site\",\n    \"Souce\": \"https://athleticgreens.com/\",\n    \"LOGO\": \"/cnt/uploads/logos/athletic-greens.jpg?1646917217\",\n    \"Effective_date\": \"2022-03-11T02:52:00-08:00\",\n    \"check_date\": \"2022-07-06T00:15:47-07:00\",\n    \"Expire_date\": \"2022-07-06T00:15:47-07:00\",\n    \"img_link\": \"https://coupons.cnet.com/image/eyJrZXkiOiJjbnQvdXBsb2Fkcy9sb2dvcy9hdGhsZXRpYy1ncmVlbnMuanBnIiwib3V0cHV0Rm9ybWF0IjoiIiwiZWRpdHMiOnsicmVzaXplIjp7IndpZHRoIjoxMTcwfX19?1646917217\",\n    \"cmp_desc\": \"NA\",\n    \"cmp_title\": \"Athletic Greens Coupons in January 2023\"\n  },\n  {\n    \"company\": \"athletic-greens\",\n    \"Shop\": \"Athletic Greens\",\n    \"LABLE\": \"$20\",\n    \"Desc\": \"Click Here to Use this Athletic Greens Offer: $20 off Single Subscriptions\",\n    \"Code\": \"Discount Displayed on Site\",\n    \"Souce\": \"https://athleticgreens.com/\",\n    \"LOGO\": \"/cnt/uploads/logos/athletic-greens.jpg?1646917217\",\n    \"Effective_date\": \"2022-03-11T02:51:00-08:00\",\n    \"check_date\": \"2022-07-06T00:16:01-07:00\",\n    \"Expire_date\": \"2022-07-06T00:16:00-07:00\",\n    \"img_link\": \"https://coupons.cnet.com/image/eyJrZXkiOiJjbnQvdXBsb2Fkcy9sb2dvcy9hdGhsZXRpYy1ncmVlbnMuanBnIiwib3V0cHV0Rm9ybWF0IjoiIiwiZWRpdHMiOnsicmVzaXplIjp7IndpZHRoIjoxMTcwfX19?1646917217\",\n    \"cmp_desc\": \"NA\",\n    \"cmp_title\": \"Athletic Greens Coupons in January 2023\"\n  },\n  {\n    \"company\": \"athletic-greens\",\n    \"Shop\": \"Athletic Greens\",\n    \"LABLE\": \"NA\",\n    \"Desc\": \"Free Gift with any Purchase at Athletic Greens\",\n    \"Code\": \"LEX\",\n    \"Souce\": \"https://athleticgreens.com/\",\n    \"LOGO\": \"/cnt/uploads/logos/athletic-greens.jpg?1646917217\",\n    \"Effective_date\": \"2022-03-13T06:06:00-07:00\",\n    \"check_date\": \"2022-05-13T00:20:40-07:00\",\n    \"Expire_date\": \"2022-05-13T00:20:40-07:00\",\n    \"img_link\": \"https://coupons.cnet.com/image/eyJrZXkiOiJjbnQvdXBsb2Fkcy9sb2dvcy9hdGhsZXRpYy1ncmVlbnMuanBnIiwib3V0cHV0Rm9ybWF0IjoiIiwiZWRpdHMiOnsicmVzaXplIjp7IndpZHRoIjoxMTcwfX19?1646917217\",\n    \"cmp_desc\": \"NA\",\n    \"cmp_title\": \"Athletic Greens Coupons in January 2023\"\n  },\n  {\n    \"company\": \"athletic-greens\",\n    \"Shop\": \"Athletic Greens\",\n    \"LABLE\": \"NA\",\n    \"Desc\": \"Athletic Greens Coupon: Free Gift with any Purchase\",\n    \"Code\": \"ROGAN\",\n    \"Souce\": \"https://athleticgreens.com/\",\n    \"LOGO\": \"/cnt/uploads/logos/athletic-greens.jpg?1646917217\",\n    \"Effective_date\": \"2022-03-12T23:55:00-08:00\",\n    \"check_date\": \"2022-03-13T08:58:11-07:00\",\n    \"Expire_date\": \"2022-03-13T08:58:11-07:00\",\n    \"img_link\": \"https://coupons.cnet.com/image/eyJrZXkiOiJjbnQvdXBsb2Fkcy9sb2dvcy9hdGhsZXRpYy1ncmVlbnMuanBnIiwib3V0cHV0Rm9ybWF0IjoiIiwiZWRpdHMiOnsicmVzaXplIjp7IndpZHRoIjoxMTcwfX19?1646917217\",\n    \"cmp_desc\": \"NA\",\n    \"cmp_title\": \"Athletic Greens Coupons in January 2023\"\n  },\n  {\n    \"company\": \"athletic-greens\",\n    \"Shop\": \"Vitamin World\",\n    \"LABLE\": \"80%\",\n    \"Desc\": \"Today only: 80% off\",\n    \"Code\": \"VWSW546\",\n    \"Souce\": \"https://www.vitaminworld.com/\",\n    \"LOGO\": \"/cnt/uploads/logos/vitamin-world.jpg?1606894191\",\n    \"Effective_date\": \"2022-12-27T02:02:00-08:00\",\n    \"check_date\": \"NA\",\n    \"Expire_date\": \"NA\",\n    \"img_link\": \"https://coupons.cnet.com/image/eyJrZXkiOiJjbnQvdXBsb2Fkcy9sb2dvcy9hdGhsZXRpYy1ncmVlbnMuanBnIiwib3V0cHV0Rm9ybWF0IjoiIiwiZWRpdHMiOnsicmVzaXplIjp7IndpZHRoIjoxMTcwfX19?1646917217\",\n    \"cmp_desc\": \"NA\",\n    \"cmp_title\": \"Athletic Greens Coupons in January 2023\"\n  },\n  {\n    \"company\": \"athletic-greens\",\n    \"Shop\": \"GNC\",\n    \"LABLE\": \"$30\",\n    \"Desc\": \"GNC Promo Code: $30 off Sitewide\",\n    \"Code\": \"NEWYEAR\",\n    \"Souce\": \"https://www.gnc.com/\",\n    \"LOGO\": \"/cnt/uploads/logos/gnc.jpg?1606894191\",\n    \"Effective_date\": \"2023-01-01T00:00:00-08:00\",\n    \"check_date\": \"NA\",\n    \"Expire_date\": \"2023-01-08T23:59:59-08:00\",\n    \"img_link\": \"https://coupons.cnet.com/image/eyJrZXkiOiJjbnQvdXBsb2Fkcy9sb2dvcy9hdGhsZXRpYy1ncmVlbnMuanBnIiwib3V0cHV0Rm9ybWF0IjoiIiwiZWRpdHMiOnsicmVzaXplIjp7IndpZHRoIjoxMTcwfX19?1646917217\",\n    \"cmp_desc\": \"NA\",\n    \"cmp_title\": \"Athletic Greens Coupons in January 2023\"\n  },\n  {\n    \"company\": \"athletic-greens\",\n    \"Shop\": \"Swanson Vitamins\",\n    \"LABLE\": \"20%\",\n    \"Desc\": \"Swanson Vitamins Promo Code: 20% off Sitewide\",\n    \"Code\": \"20TEXT\",\n    \"Souce\": \"https://www.swansonvitamins.com/\",\n    \"LOGO\": \"/cnt/uploads/logos/swanson-vitamins.jpg?1606894191\",\n    \"Effective_date\": \"2022-06-14T19:29:00-07:00\",\n    \"check_date\": \"2023-01-02T01:03:41-08:00\",\n    \"Expire_date\": \"NA\",\n    \"img_link\": \"https://coupons.cnet.com/image/eyJrZXkiOiJjbnQvdXBsb2Fkcy9sb2dvcy9hdGhsZXRpYy1ncmVlbnMuanBnIiwib3V0cHV0Rm9ybWF0IjoiIiwiZWRpdHMiOnsicmVzaXplIjp7IndpZHRoIjoxMTcwfX19?1646917217\",\n    \"cmp_desc\": \"NA\",\n    \"cmp_title\": \"Athletic Greens Coupons in January 2023\"\n  },\n  {\n    \"company\": \"athletic-greens\",\n    \"Shop\": \"iHerb\",\n    \"LABLE\": \"20%\",\n    \"Desc\": \"Grab 20% off\",\n    \"Code\": \"NEW20\",\n    \"Souce\": \"https://www.iherb.com/\",\n    \"LOGO\": \"/cnt/uploads/logos/iherb.jpg?1664355252\",\n    \"Effective_date\": \"2022-10-16T21:55:00-07:00\",\n    \"check_date\": \"2022-10-18T12:44:18-07:00\",\n    \"Expire_date\": \"NA\",\n    \"img_link\": \"https://coupons.cnet.com/image/eyJrZXkiOiJjbnQvdXBsb2Fkcy9sb2dvcy9hdGhsZXRpYy1ncmVlbnMuanBnIiwib3V0cHV0Rm9ybWF0IjoiIiwiZWRpdHMiOnsicmVzaXplIjp7IndpZHRoIjoxMTcwfX19?1646917217\",\n    \"cmp_desc\": \"NA\",\n    \"cmp_title\": \"Athletic Greens Coupons in January 2023\"\n  }\n]"]
